{
	"info": {
		"_postman_id": "75b31c82-3d08-4c02-ae97-9539bf02d123",
		"name": "Test EWM - Comments",
		"schema": "https://schema.getpostman.com/json/collection/v2.1.0/collection.json",
		"_exporter_id": "45702351"
	},
	"item": [
		{
			"name": "Создание комментария у неопубликованного события",
			"event": [
				{
					"listen": "test",
					"script": {
						"exec": [
							"pm.test(\"Ответ должен содержать код статуса 409 и данные в формате json\", function () {\r",
							"    pm.response.to.have.status(409);  \r",
							"    pm.response.to.be.withBody;\r",
							"    pm.response.to.be.json;\r",
							"});"
						],
						"type": "text/javascript",
						"packages": {},
						"requests": {}
					}
				}
			],
			"request": {
				"method": "POST",
				"header": [
					{
						"key": "Accept",
						"value": "application/json",
						"type": "text"
					}
				],
				"body": {
					"mode": "raw",
					"raw": "{\r\n    \"text\": \"nice one!\"\r\n}",
					"options": {
						"raw": {
							"language": "json"
						}
					}
				},
				"url": {
					"raw": "http://localhost:8080/1/comments/1",
					"protocol": "http",
					"host": [
						"localhost"
					],
					"port": "8080",
					"path": [
						"1",
						"comments",
						"1"
					]
				}
			},
			"response": []
		},
		{
			"name": "Публикация события 1",
			"event": [
				{
					"listen": "test",
					"script": {
						"exec": [
							"pm.test(\"Ответ должен содержать код статуса 200 и данные в формате json\", function () {\r",
							"    pm.response.to.have.status(200);\r",
							"    pm.response.to.be.withBody;\r",
							"    pm.response.to.be.json;\r",
							"});"
						],
						"type": "text/javascript",
						"packages": {},
						"requests": {}
					}
				}
			],
			"request": {
				"method": "PATCH",
				"header": [
					{
						"key": "Accept",
						"value": "application/json",
						"type": "text"
					}
				],
				"body": {
					"mode": "raw",
					"raw": "{\r\n    \"stateAction\": \"PUBLISH_EVENT\"\r\n}",
					"options": {
						"raw": {
							"language": "json"
						}
					}
				},
				"url": {
					"raw": "http://localhost:8080/admin/events/1",
					"protocol": "http",
					"host": [
						"localhost"
					],
					"port": "8080",
					"path": [
						"admin",
						"events",
						"1"
					]
				}
			},
			"response": []
		},
		{
			"name": "Создание нового комментария",
			"event": [
				{
					"listen": "test",
					"script": {
						"exec": [
							"\r",
							"pm.test(\"Ответ должен содержать код статуса 201 и данные в формате json\", function () {\r",
							"    pm.response.to.have.status(201);\r",
							"    pm.response.to.be.withBody;\r",
							"    pm.response.to.be.json;\r",
							"});"
						],
						"type": "text/javascript",
						"packages": {},
						"requests": {}
					}
				}
			],
			"request": {
				"method": "POST",
				"header": [
					{
						"key": "Accept",
						"value": "application/json",
						"type": "text"
					}
				],
				"body": {
					"mode": "raw",
					"raw": "{\r\n    \"text\": \"cool!\"\r\n}",
					"options": {
						"raw": {
							"language": "json"
						}
					}
				},
				"url": {
					"raw": "http://localhost:8080/1/comments/1",
					"protocol": "http",
					"host": [
						"localhost"
					],
					"port": "8080",
					"path": [
						"1",
						"comments",
						"1"
					]
				}
			},
			"response": []
		},
		{
			"name": "Создание комментария пустой текст",
			"event": [
				{
					"listen": "test",
					"script": {
						"exec": [
							"pm.test(\"Ответ должен содержать код статуса 400 и данные в формате json\", function () {\r",
							"    pm.response.to.have.status(400);  \r",
							"    pm.response.to.be.withBody;\r",
							"    pm.response.to.be.json;\r",
							"});"
						],
						"type": "text/javascript",
						"packages": {},
						"requests": {}
					}
				}
			],
			"request": {
				"method": "POST",
				"header": [
					{
						"key": "Accept",
						"value": "application/json",
						"type": "text"
					}
				],
				"body": {
					"mode": "raw",
					"raw": "{\r\n    \"text\": \"\"\r\n}",
					"options": {
						"raw": {
							"language": "json"
						}
					}
				},
				"url": {
					"raw": "http://localhost:8080/1/comments/1",
					"protocol": "http",
					"host": [
						"localhost"
					],
					"port": "8080",
					"path": [
						"1",
						"comments",
						"1"
					]
				}
			},
			"response": []
		},
		{
			"name": "Создание комментария текст >2000",
			"event": [
				{
					"listen": "test",
					"script": {
						"exec": [
							"pm.test(\"Ответ должен содержать код статуса 400 и данные в формате json\", function () {\r",
							"    pm.response.to.have.status(400);  \r",
							"    pm.response.to.be.withBody;\r",
							"    pm.response.to.be.json;\r",
							"});"
						],
						"type": "text/javascript",
						"packages": {},
						"requests": {}
					}
				}
			],
			"request": {
				"method": "POST",
				"header": [
					{
						"key": "Accept",
						"value": "application/json",
						"type": "text"
					}
				],
				"body": {
					"mode": "raw",
					"raw": "{\r\n    \"text\": \"Лисград встретил Айлу дождем. Обстоятельство довольно удачное — желающих мокнуть было мало, и никто не мешал таскать вещи из грузовика в магазин. Однако из-за дождя же приходилось спешить с разгрузкой, чтобы мебель не успела сильно отсыреть. Дело двигалось медленно. Айла неплохо справлялась с мелочами типа стульев и небольших цветочных горшков, но при перетаскивании дивана стала скорее обузой вызвавшемуся помочь шоферу. В конце концов он не выдержал и отправил ее заниматься растениями дальше, чтобы под ногами не путалась. Без Айлы диван удалось дотолкать до входа, но там он уперся в ступеньки, а впереди был еще второй этаж. — Девушка, а разобрать его нельзя? — хорошая мысля пришла поздновато, но все же пришла. — Нет, к сожалению, только если полностью, включая обивку. Шофер с досадой пнул диван и ушел на перекур. Вся мелкая мебель и цветы уже были в доме, а добровольный грузчик пока не спешил возвращаться. Айла села на ступеньку у входа. — Есть ли какая-то особая идея в диване, стоящем поперек тротуара? Может, вам нужна помощь? Айла подняла голову. Над ней стоял высокий человек в дождевике. Лица неравнодушного прохожего было толком не разглядеть в дождливых сумерках, но едва ли был смысл его разглядывать — знакомых в Лисграде у нее все равно не было. Девушка дружелюбно улыбнулась: — Да, помощь бы не помешала, спасибо! Подождите минутку — я позову шофера. Вдвоем управились быстро. Шофер получил расчет и уехал, а новому знакомому, представившемуся Лукой, Айла предложила остаться на чай. Придумать тему разговора сходу не получилось, и девушка пыталась тянуть время, делая вид, что никак не может выбрать, какой купаж больше подойдет для спонтанного чаепития с незнакомцем. — Вы впервые в Лисграде? — он будто почувствовал, что ей снова нужна помощь. — Что? — Айла чуть не выронила очередную банку с чаем. — А, нет, не совсем. Я приезжала пару месяцев назад посмотреть здание. Будете… — она бросила быстрый взгляд на надпись на банке, — зеленый с земляникой? — Да, пожалуйста, — подбадривающе улыбнулся Лука. От волнения руки немного тряслись, она стукнулась головой о дверцу подвесного шкафчика, пару раз едва не просыпала листья и почти уронила чайник, но всё же справилась. Закончив с заваркой и разлив чай по чашкам, Айла решилась продолжить разговор: — А вы местный? — Да, — до того дежурно вежливая, на мгновение улыбка Луки стала искренне грустной. Он поспешил спрятать ее за краем чашки, прежде чем продолжить. — Прожил здесь почти всю жизнь, только на учебу уезжал на пару лет. — А где учились?\"\r\n}",
					"options": {
						"raw": {
							"language": "json"
						}
					}
				},
				"url": {
					"raw": "http://localhost:8080/1/comments/1",
					"protocol": "http",
					"host": [
						"localhost"
					],
					"port": "8080",
					"path": [
						"1",
						"comments",
						"1"
					]
				}
			},
			"response": []
		},
		{
			"name": "Создание комментария несуществующим пользователем",
			"event": [
				{
					"listen": "test",
					"script": {
						"exec": [
							"pm.test(\"Ответ должен содержать код статуса 404 и данные в формате json\", function () {\r",
							"    pm.response.to.have.status(404);  \r",
							"    pm.response.to.be.withBody;\r",
							"    pm.response.to.be.json;\r",
							"});"
						],
						"type": "text/javascript",
						"packages": {},
						"requests": {}
					}
				}
			],
			"request": {
				"method": "POST",
				"header": [
					{
						"key": "Accept",
						"value": "application/json",
						"type": "text"
					}
				],
				"body": {
					"mode": "raw",
					"raw": "{\r\n    \"text\": \"Лисград встретил Айлу дождем. Обстоятельство довольно удачное — желающих мокнуть было мало, и никто не мешал таскать вещи из грузовика в магазин. Однако из-за дождя же приходилось спешить с разгрузкой, чтобы мебель не успела сильно отсыреть. Дело двигалось медленно. Айла неплохо справлялась с мелочами типа стульев и небольших цветочных горшков, но при перетаскивании дивана стала скорее обузой вызвавшемуся помочь шоферу. В конце концов он не выдержал и отправил ее заниматься растениями дальше, чтобы под ногами не путалась. Без Айлы диван удалось дотолкать до входа, но там он уперся в ступеньки, а впереди был еще второй этаж. — Девушка, а разобрать его нельзя? — хорошая мысля пришла поздновато, но все же пришла. — Нет, к сожалению, только если полностью, включая обивку. Шофер с досадой пнул диван и ушел на перекур. Вся мелкая мебель и цветы уже были в доме, а добровольный грузчик пока не спешил возвращаться. Айла села на ступеньку у входа. — Есть ли какая-то особая идея в диване, стоящем поперек тротуара? Может, вам нужна помощь? Айла подняла голову. Над ней стоял высокий человек в дождевике. Лица неравнодушного прохожего было толком не разглядеть в дождливых сумерках, но едва ли был смысл его разглядывать — знакомых в Лисграде у нее все равно не было. Девушка дружелюбно улыбнулась: — Да, помощь бы не помешала, спасибо! Подождите минутку — я позову шофера. Вдвоем управились быстро. Шофер получил расчет и уехал, а новому знакомому, представившемуся Лукой, Айла предложила остаться на чай. Придумать тему разговора сходу не получилось, и девушка пыталась тянуть время, делая вид, что никак не может выбрать, какой купаж больше подойдет для спонтанного чаепития с незнакомцем. — Вы впервые в Лисграде? — он будто почувствовал, что ей снова нужна помощь. — Что? — Айла чуть не выронила очередную банку с чаем. — А, нет, не совсем. Я приезжала пару месяцев назад посмотреть здание. Будете… — она бросила быстрый взгляд на надпись на банке, — зеленый с земляникой? — Да, пожалуйста, — подбадривающе улыбнулся Лука. От волнения руки немного тряслись, она стукнулась головой о дверцу подвесного шкафчика, пару раз едва не просыпала листья и почти уронила чайник, но всё же справилась. Закончив с заваркой и разлив чай по чашкам, Айла решилась продолжить разговор: — А вы местный? — Да, — до того дежурно вежливая, на мгновение улыбка Луки стала искренне грустной. Он поспешил спрятать ее за краем чашки, прежде чем продолжить. — Прожил здесь почти всю жизнь, только на учебу уезжал на пару лет. — А где учились?\"\r\n}",
					"options": {
						"raw": {
							"language": "json"
						}
					}
				},
				"url": {
					"raw": "http://localhost:8080/10000000/comments/1",
					"protocol": "http",
					"host": [
						"localhost"
					],
					"port": "8080",
					"path": [
						"10000000",
						"comments",
						"1"
					]
				}
			},
			"response": []
		},
		{
			"name": "Создание комментария у несуществующего события",
			"event": [
				{
					"listen": "test",
					"script": {
						"exec": [
							"pm.test(\"Ответ должен содержать код статуса 404 и данные в формате json\", function () {\r",
							"    pm.response.to.have.status(404);  \r",
							"    pm.response.to.be.withBody;\r",
							"    pm.response.to.be.json;\r",
							"});"
						],
						"type": "text/javascript",
						"packages": {},
						"requests": {}
					}
				}
			],
			"request": {
				"method": "POST",
				"header": [
					{
						"key": "Accept",
						"value": "application/json",
						"type": "text"
					}
				],
				"body": {
					"mode": "raw",
					"raw": "{\r\n    \"text\": \"nice one!\"\r\n}",
					"options": {
						"raw": {
							"language": "json"
						}
					}
				},
				"url": {
					"raw": "http://localhost:8080/1/comments/10000000",
					"protocol": "http",
					"host": [
						"localhost"
					],
					"port": "8080",
					"path": [
						"1",
						"comments",
						"10000000"
					]
				}
			},
			"response": []
		},
		{
			"name": "Обновление комментария",
			"event": [
				{
					"listen": "test",
					"script": {
						"exec": [
							"pm.test(\"Ответ должен содержать код статуса 200 и данные в формате json\", function () {\r",
							"    pm.response.to.have.status(200);\r",
							"    pm.response.to.be.withBody;\r",
							"    pm.response.to.be.json;\r",
							"});"
						],
						"type": "text/javascript",
						"packages": {},
						"requests": {}
					}
				}
			],
			"request": {
				"method": "PATCH",
				"header": [
					{
						"key": "Accept",
						"value": "application/json",
						"type": "text"
					}
				],
				"body": {
					"mode": "raw",
					"raw": "{\r\n    \"text\": \"cool!cool!cool!\"\r\n}",
					"options": {
						"raw": {
							"language": "json"
						}
					}
				},
				"url": {
					"raw": "http://localhost:8080/1/comments/1",
					"protocol": "http",
					"host": [
						"localhost"
					],
					"port": "8080",
					"path": [
						"1",
						"comments",
						"1"
					]
				}
			},
			"response": []
		},
		{
			"name": "Обновление комментария пустой текст",
			"event": [
				{
					"listen": "test",
					"script": {
						"exec": [
							"pm.test(\"Ответ должен содержать код статуса 400 и данные в формате json\", function () {\r",
							"    pm.response.to.have.status(400);  \r",
							"    pm.response.to.be.withBody;\r",
							"    pm.response.to.be.json;\r",
							"});"
						],
						"type": "text/javascript",
						"packages": {},
						"requests": {}
					}
				}
			],
			"request": {
				"method": "PATCH",
				"header": [
					{
						"key": "Accept",
						"value": "application/json",
						"type": "text"
					}
				],
				"body": {
					"mode": "raw",
					"raw": "{\r\n    \"text\": \"\"\r\n}",
					"options": {
						"raw": {
							"language": "json"
						}
					}
				},
				"url": {
					"raw": "http://localhost:8080/1/comments/1",
					"protocol": "http",
					"host": [
						"localhost"
					],
					"port": "8080",
					"path": [
						"1",
						"comments",
						"1"
					]
				}
			},
			"response": []
		},
		{
			"name": "Обновление комментария текст >2000",
			"event": [
				{
					"listen": "test",
					"script": {
						"exec": [
							"pm.test(\"Ответ должен содержать код статуса 400 и данные в формате json\", function () {\r",
							"    pm.response.to.have.status(400);  \r",
							"    pm.response.to.be.withBody;\r",
							"    pm.response.to.be.json;\r",
							"});"
						],
						"type": "text/javascript",
						"packages": {},
						"requests": {}
					}
				}
			],
			"request": {
				"method": "PATCH",
				"header": [
					{
						"key": "Accept",
						"value": "application/json",
						"type": "text"
					}
				],
				"body": {
					"mode": "raw",
					"raw": "{\r\n    \"text\": \"Лисград встретил Айлу дождем. Обстоятельство довольно удачное — желающих мокнуть было мало, и никто не мешал таскать вещи из грузовика в магазин. Однако из-за дождя же приходилось спешить с разгрузкой, чтобы мебель не успела сильно отсыреть. Дело двигалось медленно. Айла неплохо справлялась с мелочами типа стульев и небольших цветочных горшков, но при перетаскивании дивана стала скорее обузой вызвавшемуся помочь шоферу. В конце концов он не выдержал и отправил ее заниматься растениями дальше, чтобы под ногами не путалась. Без Айлы диван удалось дотолкать до входа, но там он уперся в ступеньки, а впереди был еще второй этаж. — Девушка, а разобрать его нельзя? — хорошая мысля пришла поздновато, но все же пришла. — Нет, к сожалению, только если полностью, включая обивку. Шофер с досадой пнул диван и ушел на перекур. Вся мелкая мебель и цветы уже были в доме, а добровольный грузчик пока не спешил возвращаться. Айла села на ступеньку у входа. — Есть ли какая-то особая идея в диване, стоящем поперек тротуара? Может, вам нужна помощь? Айла подняла голову. Над ней стоял высокий человек в дождевике. Лица неравнодушного прохожего было толком не разглядеть в дождливых сумерках, но едва ли был смысл его разглядывать — знакомых в Лисграде у нее все равно не было. Девушка дружелюбно улыбнулась: — Да, помощь бы не помешала, спасибо! Подождите минутку — я позову шофера. Вдвоем управились быстро. Шофер получил расчет и уехал, а новому знакомому, представившемуся Лукой, Айла предложила остаться на чай. Придумать тему разговора сходу не получилось, и девушка пыталась тянуть время, делая вид, что никак не может выбрать, какой купаж больше подойдет для спонтанного чаепития с незнакомцем. — Вы впервые в Лисграде? — он будто почувствовал, что ей снова нужна помощь. — Что? — Айла чуть не выронила очередную банку с чаем. — А, нет, не совсем. Я приезжала пару месяцев назад посмотреть здание. Будете… — она бросила быстрый взгляд на надпись на банке, — зеленый с земляникой? — Да, пожалуйста, — подбадривающе улыбнулся Лука. От волнения руки немного тряслись, она стукнулась головой о дверцу подвесного шкафчика, пару раз едва не просыпала листья и почти уронила чайник, но всё же справилась. Закончив с заваркой и разлив чай по чашкам, Айла решилась продолжить разговор: — А вы местный? — Да, — до того дежурно вежливая, на мгновение улыбка Луки стала искренне грустной. Он поспешил спрятать ее за краем чашки, прежде чем продолжить. — Прожил здесь почти всю жизнь, только на учебу уезжал на пару лет. — А где учились?\"\r\n}",
					"options": {
						"raw": {
							"language": "json"
						}
					}
				},
				"url": {
					"raw": "http://localhost:8080/1/comments/1",
					"protocol": "http",
					"host": [
						"localhost"
					],
					"port": "8080",
					"path": [
						"1",
						"comments",
						"1"
					]
				}
			},
			"response": []
		},
		{
			"name": "Обновление комментария несуществующим пользователем",
			"event": [
				{
					"listen": "test",
					"script": {
						"exec": [
							"pm.test(\"Ответ должен содержать код статуса 404 и данные в формате json\", function () {\r",
							"    pm.response.to.have.status(404);\r",
							"    pm.response.to.be.withBody;\r",
							"    pm.response.to.be.json;\r",
							"});"
						],
						"type": "text/javascript",
						"packages": {},
						"requests": {}
					}
				}
			],
			"request": {
				"method": "PATCH",
				"header": [
					{
						"key": "Accept",
						"value": "application/json",
						"type": "text"
					}
				],
				"body": {
					"mode": "raw",
					"raw": "{\r\n    \"text\": \"cool!cool!cool!\"\r\n}",
					"options": {
						"raw": {
							"language": "json"
						}
					}
				},
				"url": {
					"raw": "http://localhost:8080/10000000/comments/1",
					"protocol": "http",
					"host": [
						"localhost"
					],
					"port": "8080",
					"path": [
						"10000000",
						"comments",
						"1"
					]
				}
			},
			"response": []
		},
		{
			"name": "Обновление несуществующего комментария",
			"event": [
				{
					"listen": "test",
					"script": {
						"exec": [
							"pm.test(\"Ответ должен содержать код статуса 404 и данные в формате json\", function () {\r",
							"    pm.response.to.have.status(404);\r",
							"    pm.response.to.be.withBody;\r",
							"    pm.response.to.be.json;\r",
							"});"
						],
						"type": "text/javascript",
						"packages": {},
						"requests": {}
					}
				}
			],
			"request": {
				"method": "PATCH",
				"header": [
					{
						"key": "Accept",
						"value": "application/json",
						"type": "text"
					}
				],
				"body": {
					"mode": "raw",
					"raw": "{\r\n    \"text\": \"cool!cool!cool!\"\r\n}",
					"options": {
						"raw": {
							"language": "json"
						}
					}
				},
				"url": {
					"raw": "http://localhost:8080/1/comments/2",
					"protocol": "http",
					"host": [
						"localhost"
					],
					"port": "8080",
					"path": [
						"1",
						"comments",
						"2"
					]
				}
			},
			"response": []
		},
		{
			"name": "Обновление комментария не автором",
			"event": [
				{
					"listen": "test",
					"script": {
						"exec": [
							"pm.test(\"Ответ должен содержать код статуса 403 и данные в формате json\", function () {\r",
							"    pm.response.to.have.status(403);\r",
							"    pm.response.to.be.withBody;\r",
							"    pm.response.to.be.json;\r",
							"});"
						],
						"type": "text/javascript",
						"packages": {},
						"requests": {}
					}
				}
			],
			"request": {
				"method": "PATCH",
				"header": [
					{
						"key": "Accept",
						"value": "application/json",
						"type": "text"
					}
				],
				"body": {
					"mode": "raw",
					"raw": "{\r\n    \"text\": \"cool!cool!cool!\"\r\n}",
					"options": {
						"raw": {
							"language": "json"
						}
					}
				},
				"url": {
					"raw": "http://localhost:8080/2/comments/1",
					"protocol": "http",
					"host": [
						"localhost"
					],
					"port": "8080",
					"path": [
						"2",
						"comments",
						"1"
					]
				}
			},
			"response": []
		},
		{
			"name": "Получение своего комментария по id",
			"event": [
				{
					"listen": "prerequest",
					"script": {
						"exec": [
							""
						],
						"type": "text/javascript",
						"packages": {},
						"requests": {}
					}
				},
				{
					"listen": "test",
					"script": {
						"exec": [
							"pm.test(\"Ответ должен содержать код статуса 200 и данные в формате json\", function () {\r",
							"    pm.response.to.be.ok; \r",
							"    pm.response.to.be.withBody;\r",
							"    pm.response.to.be.json;\r",
							"});"
						],
						"type": "text/javascript",
						"packages": {},
						"requests": {}
					}
				}
			],
			"request": {
				"method": "GET",
				"header": [
					{
						"key": "Accept",
						"value": "application/json",
						"type": "text"
					}
				],
				"url": {
					"raw": "http://localhost:8080/1/comments/1",
					"protocol": "http",
					"host": [
						"localhost"
					],
					"port": "8080",
					"path": [
						"1",
						"comments",
						"1"
					]
				}
			},
			"response": []
		},
		{
			"name": "Получение комментария по id несуществующим пользователем",
			"event": [
				{
					"listen": "prerequest",
					"script": {
						"exec": [
							""
						],
						"type": "text/javascript",
						"packages": {},
						"requests": {}
					}
				},
				{
					"listen": "test",
					"script": {
						"exec": [
							"pm.test(\"Ответ должен содержать код статуса 404 и данные в формате json\", function () {\r",
							"    pm.response.to.have.status(404);\r",
							"    pm.response.to.be.withBody;\r",
							"    pm.response.to.be.json;\r",
							"});"
						],
						"type": "text/javascript",
						"packages": {},
						"requests": {}
					}
				}
			],
			"request": {
				"method": "GET",
				"header": [
					{
						"key": "Accept",
						"value": "application/json",
						"type": "text"
					}
				],
				"url": {
					"raw": "http://localhost:8080/10000000/comments/1",
					"protocol": "http",
					"host": [
						"localhost"
					],
					"port": "8080",
					"path": [
						"10000000",
						"comments",
						"1"
					]
				}
			},
			"response": []
		},
		{
			"name": "Получение чужого комментария по id",
			"event": [
				{
					"listen": "prerequest",
					"script": {
						"exec": [
							""
						],
						"type": "text/javascript",
						"packages": {},
						"requests": {}
					}
				},
				{
					"listen": "test",
					"script": {
						"exec": [
							"pm.test(\"Ответ должен содержать код статуса 403 и данные в формате json\", function () {\r",
							"    pm.response.to.have.status(403);\r",
							"    pm.response.to.be.withBody;\r",
							"    pm.response.to.be.json;\r",
							"});"
						],
						"type": "text/javascript",
						"packages": {},
						"requests": {}
					}
				}
			],
			"request": {
				"method": "GET",
				"header": [
					{
						"key": "Accept",
						"value": "application/json",
						"type": "text"
					}
				],
				"url": {
					"raw": "http://localhost:8080/2/comments/1",
					"protocol": "http",
					"host": [
						"localhost"
					],
					"port": "8080",
					"path": [
						"2",
						"comments",
						"1"
					]
				}
			},
			"response": []
		},
		{
			"name": "Получение всех своих комментариев",
			"event": [
				{
					"listen": "prerequest",
					"script": {
						"exec": [
							""
						],
						"type": "text/javascript",
						"packages": {},
						"requests": {}
					}
				},
				{
					"listen": "test",
					"script": {
						"exec": [
							"pm.test(\"Ответ должен содержать код статуса 200 и данные в формате json\", function () {\r",
							"    pm.response.to.be.ok; \r",
							"    pm.response.to.be.withBody;\r",
							"    pm.response.to.be.json;\r",
							"});"
						],
						"type": "text/javascript",
						"packages": {},
						"requests": {}
					}
				}
			],
			"request": {
				"method": "GET",
				"header": [
					{
						"key": "Accept",
						"value": "application/json",
						"type": "text"
					}
				],
				"url": {
					"raw": "http://localhost:8080/1/comments",
					"protocol": "http",
					"host": [
						"localhost"
					],
					"port": "8080",
					"path": [
						"1",
						"comments"
					],
					"query": [
						{
							"key": "from",
							"value": "0",
							"disabled": true
						},
						{
							"key": "size",
							"value": "10",
							"disabled": true
						}
					]
				}
			},
			"response": []
		},
		{
			"name": "Получение всех комментариев несуществующего пользователя",
			"event": [
				{
					"listen": "prerequest",
					"script": {
						"exec": [
							""
						],
						"type": "text/javascript",
						"packages": {},
						"requests": {}
					}
				},
				{
					"listen": "test",
					"script": {
						"exec": [
							"pm.test(\"Ответ должен содержать код статуса 404 и данные в формате json\", function () {\r",
							"    pm.response.to.have.status(404);\r",
							"    pm.response.to.be.withBody;\r",
							"    pm.response.to.be.json;\r",
							"});"
						],
						"type": "text/javascript",
						"packages": {},
						"requests": {}
					}
				}
			],
			"request": {
				"method": "GET",
				"header": [
					{
						"key": "Accept",
						"value": "application/json",
						"type": "text"
					}
				],
				"url": {
					"raw": "http://localhost:8080/10000000/comments",
					"protocol": "http",
					"host": [
						"localhost"
					],
					"port": "8080",
					"path": [
						"10000000",
						"comments"
					],
					"query": [
						{
							"key": "from",
							"value": "0",
							"disabled": true
						},
						{
							"key": "size",
							"value": "10",
							"disabled": true
						}
					]
				}
			},
			"response": []
		},
		{
			"name": "Получение комментария по id администратором",
			"event": [
				{
					"listen": "prerequest",
					"script": {
						"exec": [
							""
						],
						"type": "text/javascript",
						"packages": {},
						"requests": {}
					}
				},
				{
					"listen": "test",
					"script": {
						"exec": [
							"pm.test(\"Ответ должен содержать код статуса 200 и данные в формате json\", function () {\r",
							"    pm.response.to.be.ok; \r",
							"    pm.response.to.be.withBody;\r",
							"    pm.response.to.be.json;\r",
							"});"
						],
						"type": "text/javascript",
						"packages": {},
						"requests": {}
					}
				}
			],
			"request": {
				"method": "GET",
				"header": [
					{
						"key": "Accept",
						"value": "application/json",
						"type": "text"
					}
				],
				"url": {
					"raw": "http://localhost:8080/admin/comments/1",
					"protocol": "http",
					"host": [
						"localhost"
					],
					"port": "8080",
					"path": [
						"admin",
						"comments",
						"1"
					]
				}
			},
			"response": []
		},
		{
			"name": "Получение несуществующего комментария по id администратором",
			"event": [
				{
					"listen": "prerequest",
					"script": {
						"exec": [
							""
						],
						"type": "text/javascript",
						"packages": {},
						"requests": {}
					}
				},
				{
					"listen": "test",
					"script": {
						"exec": [
							"pm.test(\"Ответ должен содержать код статуса 404 и данные в формате json\", function () {\r",
							"    pm.response.to.have.status(404);\r",
							"    pm.response.to.be.withBody;\r",
							"    pm.response.to.be.json;\r",
							"});"
						],
						"type": "text/javascript",
						"packages": {},
						"requests": {}
					}
				}
			],
			"request": {
				"method": "GET",
				"header": [
					{
						"key": "Accept",
						"value": "application/json",
						"type": "text"
					}
				],
				"url": {
					"raw": "http://localhost:8080/admin/comments/2",
					"protocol": "http",
					"host": [
						"localhost"
					],
					"port": "8080",
					"path": [
						"admin",
						"comments",
						"2"
					]
				}
			},
			"response": []
		},
		{
			"name": "Получение всех комментариев пользователя админом",
			"event": [
				{
					"listen": "prerequest",
					"script": {
						"exec": [
							""
						],
						"type": "text/javascript",
						"packages": {},
						"requests": {}
					}
				},
				{
					"listen": "test",
					"script": {
						"exec": [
							"pm.test(\"Ответ должен содержать код статуса 200 и данные в формате json\", function () {\r",
							"    pm.response.to.be.ok; \r",
							"    pm.response.to.be.withBody;\r",
							"    pm.response.to.be.json;\r",
							"});"
						],
						"type": "text/javascript",
						"packages": {},
						"requests": {}
					}
				}
			],
			"request": {
				"method": "GET",
				"header": [
					{
						"key": "Accept",
						"value": "application/json",
						"type": "text"
					}
				],
				"url": {
					"raw": "http://localhost:8080/admin/comments/users/1",
					"protocol": "http",
					"host": [
						"localhost"
					],
					"port": "8080",
					"path": [
						"admin",
						"comments",
						"users",
						"1"
					],
					"query": [
						{
							"key": "from",
							"value": "0",
							"disabled": true
						},
						{
							"key": "size",
							"value": "10",
							"disabled": true
						}
					]
				}
			},
			"response": []
		},
		{
			"name": "Получение всех комментариев несуществующего пользователя админом",
			"event": [
				{
					"listen": "prerequest",
					"script": {
						"exec": [
							""
						],
						"type": "text/javascript",
						"packages": {},
						"requests": {}
					}
				},
				{
					"listen": "test",
					"script": {
						"exec": [
							"pm.test(\"Ответ должен содержать код статуса 404 и данные в формате json\", function () {\r",
							"    pm.response.to.have.status(404);\r",
							"    pm.response.to.be.withBody;\r",
							"    pm.response.to.be.json;\r",
							"});"
						],
						"type": "text/javascript",
						"packages": {},
						"requests": {}
					}
				}
			],
			"request": {
				"method": "GET",
				"header": [
					{
						"key": "Accept",
						"value": "application/json",
						"type": "text"
					}
				],
				"url": {
					"raw": "http://localhost:8080/admin/comments/users/10000000",
					"protocol": "http",
					"host": [
						"localhost"
					],
					"port": "8080",
					"path": [
						"admin",
						"comments",
						"users",
						"10000000"
					],
					"query": [
						{
							"key": "from",
							"value": "0",
							"disabled": true
						},
						{
							"key": "size",
							"value": "10",
							"disabled": true
						}
					]
				}
			},
			"response": []
		},
		{
			"name": "Получение всех комментариев события админом",
			"event": [
				{
					"listen": "prerequest",
					"script": {
						"exec": [
							""
						],
						"type": "text/javascript",
						"packages": {},
						"requests": {}
					}
				},
				{
					"listen": "test",
					"script": {
						"exec": [
							"pm.test(\"Ответ должен содержать код статуса 200 и данные в формате json\", function () {\r",
							"    pm.response.to.be.ok; \r",
							"    pm.response.to.be.withBody;\r",
							"    pm.response.to.be.json;\r",
							"});"
						],
						"type": "text/javascript",
						"packages": {},
						"requests": {}
					}
				}
			],
			"request": {
				"method": "GET",
				"header": [
					{
						"key": "Accept",
						"value": "application/json",
						"type": "text"
					}
				],
				"url": {
					"raw": "http://localhost:8080/admin/comments/events/1",
					"protocol": "http",
					"host": [
						"localhost"
					],
					"port": "8080",
					"path": [
						"admin",
						"comments",
						"events",
						"1"
					],
					"query": [
						{
							"key": "from",
							"value": "0",
							"disabled": true
						},
						{
							"key": "size",
							"value": "10",
							"disabled": true
						}
					]
				}
			},
			"response": []
		},
		{
			"name": "Получение всех комментариев несуществующего события админом",
			"event": [
				{
					"listen": "prerequest",
					"script": {
						"exec": [
							""
						],
						"type": "text/javascript",
						"packages": {},
						"requests": {}
					}
				},
				{
					"listen": "test",
					"script": {
						"exec": [
							"pm.test(\"Ответ должен содержать код статуса 404 и данные в формате json\", function () {\r",
							"    pm.response.to.have.status(404);\r",
							"    pm.response.to.be.withBody;\r",
							"    pm.response.to.be.json;\r",
							"});"
						],
						"type": "text/javascript",
						"packages": {},
						"requests": {}
					}
				}
			],
			"request": {
				"method": "GET",
				"header": [
					{
						"key": "Accept",
						"value": "application/json",
						"type": "text"
					}
				],
				"url": {
					"raw": "http://localhost:8080/admin/comments/events/10000000",
					"protocol": "http",
					"host": [
						"localhost"
					],
					"port": "8080",
					"path": [
						"admin",
						"comments",
						"events",
						"10000000"
					],
					"query": [
						{
							"key": "from",
							"value": "0",
							"disabled": true
						},
						{
							"key": "size",
							"value": "10",
							"disabled": true
						}
					]
				}
			},
			"response": []
		},
		{
			"name": "Получение всех комментариев одного события",
			"event": [
				{
					"listen": "prerequest",
					"script": {
						"exec": [
							""
						],
						"type": "text/javascript",
						"packages": {},
						"requests": {}
					}
				},
				{
					"listen": "test",
					"script": {
						"exec": [
							"pm.test(\"Ответ должен содержать код статуса 200 и данные в формате json\", function () {\r",
							"    pm.response.to.be.ok; \r",
							"    pm.response.to.be.withBody;\r",
							"    pm.response.to.be.json;\r",
							"});"
						],
						"type": "text/javascript",
						"packages": {},
						"requests": {}
					}
				}
			],
			"request": {
				"method": "GET",
				"header": [
					{
						"key": "Accept",
						"value": "application/json",
						"type": "text"
					}
				],
				"url": {
					"raw": "http://localhost:8080/events/1/comments",
					"protocol": "http",
					"host": [
						"localhost"
					],
					"port": "8080",
					"path": [
						"events",
						"1",
						"comments"
					],
					"query": [
						{
							"key": "from",
							"value": "0",
							"disabled": true
						},
						{
							"key": "size",
							"value": "10",
							"disabled": true
						}
					]
				}
			},
			"response": []
		},
		{
			"name": "Получение всех комментариев несуществующего события",
			"event": [
				{
					"listen": "prerequest",
					"script": {
						"exec": [
							""
						],
						"type": "text/javascript",
						"packages": {},
						"requests": {}
					}
				},
				{
					"listen": "test",
					"script": {
						"exec": [
							"pm.test(\"Ответ должен содержать код статуса 200 и данные в формате json\", function () {\r",
							"    pm.response.to.be.ok; \r",
							"    pm.response.to.be.withBody;\r",
							"    pm.response.to.be.json;\r",
							"});"
						],
						"type": "text/javascript",
						"packages": {},
						"requests": {}
					}
				}
			],
			"request": {
				"method": "GET",
				"header": [
					{
						"key": "Accept",
						"value": "application/json",
						"type": "text"
					}
				],
				"url": {
					"raw": "http://localhost:8080/events/2/comments",
					"protocol": "http",
					"host": [
						"localhost"
					],
					"port": "8080",
					"path": [
						"events",
						"2",
						"comments"
					],
					"query": [
						{
							"key": "from",
							"value": "0",
							"disabled": true
						},
						{
							"key": "size",
							"value": "10",
							"disabled": true
						}
					]
				}
			},
			"response": []
		},
		{
			"name": "Удаление несуществующего комментария",
			"event": [
				{
					"listen": "test",
					"script": {
						"exec": [
							"pm.test(\"Ответ должен содержать код статуса 404\", function () {\r",
							"    pm.response.to.have.status(404);\r",
							"});"
						],
						"type": "text/javascript",
						"packages": {},
						"requests": {}
					}
				}
			],
			"request": {
				"method": "DELETE",
				"header": [
					{
						"key": "Accept",
						"value": "application/json",
						"type": "text"
					}
				],
				"url": {
					"raw": "http://localhost:8080/1/comments/2",
					"protocol": "http",
					"host": [
						"localhost"
					],
					"port": "8080",
					"path": [
						"1",
						"comments",
						"2"
					]
				}
			},
			"response": []
		},
		{
			"name": "Удаление чужого комментария",
			"event": [
				{
					"listen": "test",
					"script": {
						"exec": [
							"pm.test(\"Ответ должен содержать код статуса 403\", function () {\r",
							"    pm.response.to.have.status(403);\r",
							"});"
						],
						"type": "text/javascript",
						"packages": {},
						"requests": {}
					}
				}
			],
			"request": {
				"method": "DELETE",
				"header": [
					{
						"key": "Accept",
						"value": "application/json",
						"type": "text"
					}
				],
				"url": {
					"raw": "http://localhost:8080/2/comments/1",
					"protocol": "http",
					"host": [
						"localhost"
					],
					"port": "8080",
					"path": [
						"2",
						"comments",
						"1"
					]
				}
			},
			"response": []
		},
		{
			"name": "Удаление комментария несуществующим пользователем",
			"event": [
				{
					"listen": "test",
					"script": {
						"exec": [
							"pm.test(\"Ответ должен содержать код статуса 404\", function () {\r",
							"    pm.response.to.have.status(404);\r",
							"});"
						],
						"type": "text/javascript",
						"packages": {},
						"requests": {}
					}
				}
			],
			"request": {
				"method": "DELETE",
				"header": [
					{
						"key": "Accept",
						"value": "application/json",
						"type": "text"
					}
				],
				"url": {
					"raw": "http://localhost:8080/10000000/comments/1",
					"protocol": "http",
					"host": [
						"localhost"
					],
					"port": "8080",
					"path": [
						"10000000",
						"comments",
						"1"
					]
				}
			},
			"response": []
		},
		{
			"name": "Удаление своего комментария",
			"event": [
				{
					"listen": "test",
					"script": {
						"exec": [
							"pm.test(\"Ответ должен содержать код статуса 204\", function () {\r",
							"    pm.response.to.have.status(204);\r",
							"});"
						],
						"type": "text/javascript",
						"packages": {},
						"requests": {}
					}
				}
			],
			"request": {
				"method": "DELETE",
				"header": [
					{
						"key": "Accept",
						"value": "application/json",
						"type": "text"
					}
				],
				"url": {
					"raw": "http://localhost:8080/1/comments/1",
					"protocol": "http",
					"host": [
						"localhost"
					],
					"port": "8080",
					"path": [
						"1",
						"comments",
						"1"
					]
				}
			},
			"response": []
		},
		{
			"name": "Получение своего удаленного комментария по id",
			"event": [
				{
					"listen": "prerequest",
					"script": {
						"exec": [
							""
						],
						"type": "text/javascript",
						"packages": {},
						"requests": {}
					}
				},
				{
					"listen": "test",
					"script": {
						"exec": [
							"pm.test(\"Ответ должен содержать код статуса 404 и данные в формате json\", function () {\r",
							"    pm.response.to.have.status(404);  \r",
							"    pm.response.to.be.withBody;\r",
							"    pm.response.to.be.json;\r",
							"});"
						],
						"type": "text/javascript",
						"packages": {},
						"requests": {}
					}
				}
			],
			"request": {
				"method": "GET",
				"header": [
					{
						"key": "Accept",
						"value": "application/json",
						"type": "text"
					}
				],
				"url": {
					"raw": "http://localhost:8080/1/comments/1",
					"protocol": "http",
					"host": [
						"localhost"
					],
					"port": "8080",
					"path": [
						"1",
						"comments",
						"1"
					]
				}
			},
			"response": []
		},
		{
			"name": "Создание нового комментария",
			"event": [
				{
					"listen": "test",
					"script": {
						"exec": [
							"\r",
							"pm.test(\"Ответ должен содержать код статуса 201 и данные в формате json\", function () {\r",
							"    pm.response.to.have.status(201);\r",
							"    pm.response.to.be.withBody;\r",
							"    pm.response.to.be.json;\r",
							"});"
						],
						"type": "text/javascript",
						"packages": {},
						"requests": {}
					}
				}
			],
			"request": {
				"method": "POST",
				"header": [
					{
						"key": "Accept",
						"value": "application/json",
						"type": "text"
					}
				],
				"body": {
					"mode": "raw",
					"raw": "{\r\n    \"text\": \"запрещенка\"\r\n}",
					"options": {
						"raw": {
							"language": "json"
						}
					}
				},
				"url": {
					"raw": "http://localhost:8080/1/comments/1",
					"protocol": "http",
					"host": [
						"localhost"
					],
					"port": "8080",
					"path": [
						"1",
						"comments",
						"1"
					]
				}
			},
			"response": []
		},
		{
			"name": "Удаление комментария админом",
			"event": [
				{
					"listen": "test",
					"script": {
						"exec": [
							"pm.test(\"Ответ должен содержать код статуса 204\", function () {\r",
							"    pm.response.to.have.status(204);\r",
							"});"
						],
						"type": "text/javascript",
						"packages": {},
						"requests": {}
					}
				}
			],
			"request": {
				"method": "DELETE",
				"header": [
					{
						"key": "Accept",
						"value": "application/json",
						"type": "text"
					}
				],
				"url": {
					"raw": "http://localhost:8080/admin/comments/2",
					"protocol": "http",
					"host": [
						"localhost"
					],
					"port": "8080",
					"path": [
						"admin",
						"comments",
						"2"
					]
				}
			},
			"response": []
		},
		{
			"name": "Получение своего удаленного комментария по id Copy",
			"event": [
				{
					"listen": "prerequest",
					"script": {
						"exec": [
							""
						],
						"type": "text/javascript",
						"packages": {},
						"requests": {}
					}
				},
				{
					"listen": "test",
					"script": {
						"exec": [
							"pm.test(\"Ответ должен содержать код статуса 404 и данные в формате json\", function () {\r",
							"    pm.response.to.have.status(404);  \r",
							"    pm.response.to.be.withBody;\r",
							"    pm.response.to.be.json;\r",
							"});"
						],
						"type": "text/javascript",
						"packages": {},
						"requests": {}
					}
				}
			],
			"request": {
				"method": "GET",
				"header": [
					{
						"key": "Accept",
						"value": "application/json",
						"type": "text"
					}
				],
				"url": {
					"raw": "http://localhost:8080/1/comments/1",
					"protocol": "http",
					"host": [
						"localhost"
					],
					"port": "8080",
					"path": [
						"1",
						"comments",
						"1"
					]
				}
			},
			"response": []
		},
		{
			"name": "Удаление несуществующего комментария админом",
			"event": [
				{
					"listen": "test",
					"script": {
						"exec": [
							"pm.test(\"Ответ должен содержать код статуса 204\", function () {\r",
							"    pm.response.to.have.status(204);\r",
							"});"
						],
						"type": "text/javascript",
						"packages": {},
						"requests": {}
					}
				}
			],
			"request": {
				"method": "DELETE",
				"header": [
					{
						"key": "Accept",
						"value": "application/json",
						"type": "text"
					}
				],
				"url": {
					"raw": "http://localhost:8080/admin/comments/3",
					"protocol": "http",
					"host": [
						"localhost"
					],
					"port": "8080",
					"path": [
						"admin",
						"comments",
						"3"
					]
				}
			},
			"response": []
		}
	],
	"variable": [
		{
			"key": "baseURL",
			"value": "",
			"type": "default"
		}
	]
}